lxe/__init__.py
lxe/mxe.py
lxe/rxe.py
lxe/sxe.py
lxe-0.0.1.dist-info/LICENSE
lxe-0.0.1.dist-info/METADATA
lxe-0.0.1.dist-info/WHEEL
lxe-0.0.1.dist-info/top_level.txt
lxe-0.0.1.dist-info/RECORD
